ccnp/__init__.py
ccnp/ccnp_server_pb2.py
ccnp/ccnp_server_pb2.pyi
ccnp/ccnp_server_pb2_grpc.py
ccnp/sdk.py
example/py_sdk_example.py
tests/conftest.py
tests/test_eventlog.py
tests/test_measurement.py
ccnp-0.4.0.dist-info/METADATA
ccnp-0.4.0.dist-info/WHEEL
ccnp-0.4.0.dist-info/top_level.txt
ccnp-0.4.0.dist-info/RECORD
